{
"type": "FeatureCollection",
"name": "destination_4326",
"crs": { "type": "name", "properties": { "name": "urn:ogc:def:crs:OGC:1.3:CRS84" } },
"features": [
{ "type": "Feature", "properties": { "id": 1, "Name": "Bus Stop 1" }, "geometry": null },
{ "type": "Feature", "properties": { "id": 2, "Name": "Bus Stop 2" }, "geometry": null },
{ "type": "Feature", "properties": { "id": 1, "Name": "Guggenheim Museum" }, "geometry": { "type": "Point", "coordinates": [ -73.958925317364532, 40.782922893641128 ] } }
]
}
